lion_perplexity/PerplexityModel.py
lion_perplexity/PerplexityService.py
lion_perplexity/__init__.py
lion_perplexity/perplexity_max_output_token_data.yaml
lion_perplexity/perplexity_price_data.yaml
lion_perplexity/version.py
lion_perplexity/api_endpoints/__init__.py
lion_perplexity/api_endpoints/api_request.py
lion_perplexity/api_endpoints/data_models.py
lion_perplexity/api_endpoints/match_response.py
lion_perplexity/api_endpoints/chat_completions/__init__.py
lion_perplexity/api_endpoints/chat_completions/request/__init__.py
lion_perplexity/api_endpoints/chat_completions/request/request_body.py
lion_perplexity/api_endpoints/chat_completions/response/__init__.py
lion_perplexity/api_endpoints/chat_completions/response/response_body.py
lion_perplexity-0.1.0.dist-info/METADATA
lion_perplexity-0.1.0.dist-info/WHEEL
lion_perplexity-0.1.0.dist-info/licenses/LICENSE
lion_perplexity-0.1.0.dist-info/RECORD
